{"name":"Checking unauthenticated post to questions end point fails","id":"alchemy-rest-api-page;checking-unauthenticated-post-to-questions-end-point-fails","scenarioId":"classpath:features/alchemy/rest_api:Checking unauthenticated post to questions end point fails","methodName":"Checking unauthenticated post to questions end point fails","testSteps":[{"number":1,"description":"When I upload a question set","duration":2803,"startTime":"2026-07-17T14:28:24.470718502Z[Etc/UTC]","result":"SUCCESS","precondition":false,"level":0,"children":[{"number":2,"description":"Upload an unauthenticated questions","duration":2547,"startTime":"2026-07-17T14:28:24.723450060Z[Etc/UTC]","result":"SUCCESS","precondition":false,"level":1,"children":[{"number":3,"description":"POST https://vamcjbi1o9.execute-api.eu-north-1.amazonaws.com/questions","duration":0,"startTime":"2026-07-17T14:28:29.463755872Z[Etc/UTC]","result":"SUCCESS","restQuery":{"method":"POST","path":"https://vamcjbi1o9.execute-api.eu-north-1.amazonaws.com/questions","content":"","contentType":"application/x-www-form-urlencoded","requestHeaders":"Accept\u003d*/*\n\t\t\t\tContent-Type\u003dapplication/x-www-form-urlencoded; charset\u003dISO-8859-1","requestCookies":"","responseHeaders":"Date: Fri, 17 Jul 2026 14:28:27 GMT\nContent-Type: application/json\nContent-Length: 26\nConnection: keep-alive\nwww-authenticate: Bearer\napigw-requestid: Ap5R0jjfgi0EKzg\u003d","responseCookies":"","responseBody":"{\n    \"message\": \"Unauthorized\"\n}","statusCode":401},"precondition":false,"level":2}]}]},{"number":4,"description":"Then the response should give code 401","duration":1,"startTime":"2026-07-17T14:28:27.277939136Z[Etc/UTC]","result":"SUCCESS","precondition":false,"level":0}],"userStory":{"id":"classpath:features/alchemy/rest_api","storyName":"Alchemy REST API page","displayName":"Alchemy REST API page","path":"alchemy/rest_api","pathElements":[{"name":"alchemy","description":""},{"name":"rest_api","description":""}],"type":"feature"},"title":"Checking unauthenticated post to questions end point fails","description":"","tags":[{"name":"restassured","type":"tag","displayName":"restassured","rawStringFromValueTag":"restassured"}],"startTime":"2026-07-17T14:28:24.353317670Z[Etc/UTC]","endTime":"2026-07-17T14:28:27.279565467Z[Etc/UTC]","duration":5110,"projectKey":"","isManualTestingUpToDate":false,"manual":false,"testSource":"Cucumber","result":"SUCCESS"}